tests/__init__.py
tests/manual/__init__.py
tests/manual/inject_urls_test.py
tests/manual/super_short_text_test.py
tests/manual/test_helper.py
tests/manual/text_test.py
tests/manual/webpage_test.py
tests/manual/youtube_test.py
tldrwl/__init__.py
tldrwl/__main__.py
tldrwl/ai_interface.py
tldrwl/exception.py
tldrwl/logger.py
tldrwl/register.py
tldrwl/summarize.py
tldrwl/summarizers/__init__.py
tldrwl/summarizers/chat_completions_text_summarizer.py
tldrwl/summarizers/text_summarizer.py
tldrwl/transformers/__init__.py
tldrwl/transformers/transformer.py
tldrwl/transformers/webpage_transformer.py
tldrwl/transformers/youtube_transformer.py
tldrwl-2.0.0.dist-info/METADATA
tldrwl-2.0.0.dist-info/WHEEL
tldrwl-2.0.0.dist-info/top_level.txt
tldrwl-2.0.0.dist-info/RECORD
