Metadata-Version: 2.1
Name: tldrwl
Version: 2.0.0
Summary: Too long, didn't read/watch/listen
Home-page: https://github.com/jrodal98/tldrwl
Author: Jacob Rodal
Author-email: dev@jrodal.com
Requires-Python: >=3.8
Requires-Dist: openai <2.0.0,>=1.16.2
Requires-Dist: youtube-transcript-api <0.7.0,>=0.6.0
Requires-Dist: beautifulsoup4 <5.0.0,>=4.12.0
Requires-Dist: requests <3.0.0,>=2.30.0
Requires-Dist: aiohttp <4.0.0,>=3.8.0
